superintendent/__init__.py
superintendent/_compatibility.py
superintendent/db_queue.py
superintendent/queueing_utils.py
superintendent/serialization.py
superintendent/acquisition_functions/__init__.py
superintendent/acquisition_functions/decorators.py
superintendent-0.6.0.dist-info/WHEEL
superintendent-0.6.0.dist-info/METADATA
superintendent-0.6.0.dist-info/RECORD
