Metadata-Version: 2.1
Name: superintendent
Version: 0.6.0
Summary: Interactive machine learning supervision.
Home-page: https://github.com/janfreyberg/superintendent
License: MIT
Keywords: widgets labelling annotation
Author: Jan Freyberg
Author-email: jan.freyberg@gmail.com
Requires-Python: >=3.6
Classifier: Programming Language :: Python :: 3.6
Classifier: Programming Language :: Python :: 3.7
Classifier: License :: OSI Approved :: MIT License
Classifier: Intended Audience :: Science/Research
Classifier: Framework :: Jupyter
Requires-Dist: ipywidgets>=7.4
Requires-Dist: numpy>=1.15
Requires-Dist: pandas>=0.24.0
Requires-Dist: scikit-learn>=0.20.3
Requires-Dist: scipy>=1.2
Requires-Dist: sqlalchemy>=1.3
Requires-Dist: Pillow
Requires-Dist: cachetools>=3.1
Requires-Dist: psycopg2-binary>=2.8
Requires-Dist: ipyevents>=0.6.0
Requires-Dist: typing-extensions
Requires-Dist: sqlmodel
Requires-Dist: codetiming>=1.3.0
Requires-Dist: jupyterlab>=3.0 ; extra == "dev"
Requires-Dist: rope ; extra == "dev"
Requires-Dist: sphinx>=4.0 ; extra == "doc"
Requires-Dist: requests>=2.21 ; extra == "doc"
Requires-Dist: html5lib>=1.0 ; extra == "doc"
Requires-Dist: bs4>=0.0.1 ; extra == "doc"
Requires-Dist: wordcloud>=1.5 ; extra == "doc"
Requires-Dist: myst-parser>=0.18.0 ; extra == "doc"
Requires-Dist: sphinx_rtd_theme>=0.4.3 ; extra == "doc"
Requires-Dist: jupyter-sphinx>=0.1.4 ; extra == "doc"
Requires-Dist: nbsphinx>=0.4.2 ; extra == "doc"
Requires-Dist: sphinx-automodapi ; extra == "doc"
Requires-Dist: ipyannotations>=0.5.1 ; extra == "doc"
Requires-Dist: requests>=2.21 ; extra == "examples"
Requires-Dist: html5lib>=1.0 ; extra == "examples"
Requires-Dist: bs4>=0.0.1 ; extra == "examples"
Requires-Dist: wordcloud>=1.5 ; extra == "examples"
Requires-Dist: isort>=4.3.21 ; extra == "test"
Requires-Dist: pytest>=4.1 ; extra == "test"
Requires-Dist: pytest-cov>=2.6 ; extra == "test"
Requires-Dist: hypothesis>=4.17 ; extra == "test"
Requires-Dist: pytest-helpers-namespace>=2019.1 ; extra == "test"
Requires-Dist: pytest-mock>=1.10 ; extra == "test"
Requires-Dist: nbconvert>=5.4 ; extra == "test"
Requires-Dist: coveralls>=1.7 ; extra == "test"
Requires-Dist: docargs>=0.2.0 ; extra == "test"
Requires-Dist: black>=19.3b0 ; extra == "test"
Requires-Dist: flake8>=3.7 ; extra == "test"
Requires-Dist: mypy ; extra == "test"
Requires-Dist: types-cachetools ; extra == "test"
Provides-Extra: dev
Provides-Extra: doc
Provides-Extra: examples
Provides-Extra: test
